cursofiap/__init__.py
cursofiap/core.py
cursofiap_package_temp-1.0.1.dist-info/METADATA
cursofiap_package_temp-1.0.1.dist-info/WHEEL
cursofiap_package_temp-1.0.1.dist-info/top_level.txt
cursofiap_package_temp-1.0.1.dist-info/RECORD
